klio_exec/__init__.py
klio_exec/cli.py
klio_exec/options.py
klio_exec/commands/__init__.py
klio_exec/commands/audit.py
klio_exec/commands/profile.py
klio_exec/commands/run.py
klio_exec/commands/stop.py
klio_exec/commands/audit_steps/__init__.py
klio_exec/commands/audit_steps/base.py
klio_exec/commands/audit_steps/multithreaded_tf.py
klio_exec/commands/audit_steps/numpy_broken_blas.py
klio_exec/commands/audit_steps/tempfile_usage.py
klio_exec/commands/utils/__init__.py
klio_exec/commands/utils/cpu_utils.py
klio_exec/commands/utils/memory_utils.py
klio_exec/commands/utils/plugin_utils.py
klio_exec/commands/utils/profile_utils.py
klio_exec/commands/utils/wrappers.py
klio_exec/runners/__init__.py
klio_exec/runners/evaluators.py
klio_exec/runners/gke_direct.py
klio_exec-22.3.0.dist-info/METADATA
klio_exec-22.3.0.dist-info/WHEEL
klio_exec-22.3.0.dist-info/entry_points.txt
klio_exec-22.3.0.dist-info/top_level.txt
klio_exec-22.3.0.dist-info/RECORD
