Metadata-Version: 2.1
Name: klio-exec
Version: 22.3.0
Summary: Klio pipeline executor within a job
Home-page: https://github.com/spotify/klio
Author: The klio developers
Author-email: opensource+klio@spotify.com
Maintainer: The klio developers
Maintainer-email: opensource+klio@spotify.com
License: UNKNOWN
Project-URL: Documentation, https://docs.klio.io
Project-URL: Bug Tracker, https://github.com/spotify/klio/issues
Project-URL: Source Code, https://github.com/spotify/klio
Keywords: klio,apache,beam,audio
Platform: UNKNOWN
Classifier: Development Status :: 3 - Alpha
Classifier: Natural Language :: English
Classifier: Operating System :: POSIX :: Linux
Classifier: Operating System :: MacOS :: MacOS X
Classifier: Programming Language :: Python
Classifier: Programming Language :: Python :: 3.6
Classifier: Programming Language :: Python :: 3.7
Classifier: Programming Language :: Python :: 3.8
Classifier: Programming Language :: Python :: Implementation :: CPython
Classifier: License :: OSI Approved :: Apache Software License
Classifier: Topic :: Software Development :: Libraries
Classifier: Topic :: Software Development :: Libraries :: Python Modules
Classifier: Topic :: Multimedia
Classifier: Topic :: Multimedia :: Graphics
Classifier: Topic :: Multimedia :: Sound/Audio
Classifier: Topic :: Multimedia :: Video
Classifier: Topic :: Scientific/Engineering
Classifier: Topic :: Scientific/Engineering :: Image Processing
Requires-Python: >=3.6, <3.9
Requires-Dist: attrs
Requires-Dist: click
Requires-Dist: klio-core (>=22.3.0)
Requires-Dist: klio (>=22.3.0)
Requires-Dist: pyyaml
Requires-Dist: apache-beam[gcp] (>2.21.0)
Requires-Dist: google-cloud-pubsub
Requires-Dist: setuptools
Requires-Dist: py
Requires-Dist: pytest
Requires-Dist: pytest-mock
Provides-Extra: debug
Requires-Dist: line-profiler (<3.2) ; extra == 'debug'
Requires-Dist: matplotlib ; extra == 'debug'
Requires-Dist: numpy ; extra == 'debug'
Requires-Dist: memory-profiler ; extra == 'debug'
Requires-Dist: psutil ; extra == 'debug'
Provides-Extra: dev
Requires-Dist: sphinx ; extra == 'dev'
Requires-Dist: interrogate ; extra == 'dev'
Requires-Dist: coverage ; extra == 'dev'
Requires-Dist: pytest (>=4.3.0) ; extra == 'dev'
Requires-Dist: pytest-cov ; extra == 'dev'
Requires-Dist: pytest-mock ; extra == 'dev'
Requires-Dist: PyHamcrest ; extra == 'dev'
Requires-Dist: line-profiler (<3.2) ; extra == 'dev'
Requires-Dist: matplotlib ; extra == 'dev'
Requires-Dist: numpy ; extra == 'dev'
Requires-Dist: memory-profiler ; extra == 'dev'
Requires-Dist: psutil ; extra == 'dev'
Requires-Dist: bumpversion ; extra == 'dev'
Requires-Dist: wheel ; extra == 'dev'
Provides-Extra: docs
Requires-Dist: sphinx ; extra == 'docs'
Requires-Dist: interrogate ; extra == 'docs'
Provides-Extra: tests
Requires-Dist: coverage ; extra == 'tests'
Requires-Dist: pytest (>=4.3.0) ; extra == 'tests'
Requires-Dist: pytest-cov ; extra == 'tests'
Requires-Dist: pytest-mock ; extra == 'tests'
Requires-Dist: PyHamcrest ; extra == 'tests'
